ta_box-0.0.1a1.dev5.dist-info/licenses/LICENSE
tabox/__init__.py
tabox/retcode.py
tabox/settings.py
tabox/ta_func/hilbert_transform.cp312-win_amd64.pyd
tabox/ta_func/ta_ACOS.cp312-win_amd64.pyd
tabox/ta_func/ta_AD.cp312-win_amd64.pyd
tabox/ta_func/ta_ADD.cp312-win_amd64.pyd
tabox/ta_func/ta_ADOSC.cp312-win_amd64.pyd
tabox/ta_func/ta_ADX.cp312-win_amd64.pyd
tabox/ta_func/ta_ADXR.cp312-win_amd64.pyd
tabox/ta_func/ta_APO.cp312-win_amd64.pyd
tabox/ta_func/ta_AROON.cp312-win_amd64.pyd
tabox/ta_func/ta_AROONOSC.cp312-win_amd64.pyd
tabox/ta_func/ta_ASIN.cp312-win_amd64.pyd
tabox/ta_func/ta_ATAN.cp312-win_amd64.pyd
tabox/ta_func/ta_ATR.cp312-win_amd64.pyd
tabox/ta_func/ta_AVGPRICE.cp312-win_amd64.pyd
tabox/ta_func/ta_BBANDS.cp312-win_amd64.pyd
tabox/ta_func/ta_BETA.cp312-win_amd64.pyd
tabox/ta_func/ta_BOP.cp312-win_amd64.pyd
tabox/ta_func/ta_CCI.cp312-win_amd64.pyd
tabox/ta_func/ta_CEIL.cp312-win_amd64.pyd
tabox/ta_func/ta_CMO.cp312-win_amd64.pyd
tabox/ta_func/ta_CORREL.cp312-win_amd64.pyd
tabox/ta_func/ta_COS.cp312-win_amd64.pyd
tabox/ta_func/ta_COSH.cp312-win_amd64.pyd
tabox/ta_func/ta_DEMA.cp312-win_amd64.pyd
tabox/ta_func/ta_DIV.cp312-win_amd64.pyd
tabox/ta_func/ta_DX.cp312-win_amd64.pyd
tabox/ta_func/ta_EMA.cp312-win_amd64.pyd
tabox/ta_func/ta_EXP.cp312-win_amd64.pyd
tabox/ta_func/ta_FLOOR.cp312-win_amd64.pyd
tabox/ta_func/ta_KAMA.cp312-win_amd64.pyd
tabox/ta_func/ta_LN.cp312-win_amd64.pyd
tabox/ta_func/ta_LOG10.cp312-win_amd64.pyd
tabox/ta_func/ta_MA.cp312-win_amd64.pyd
tabox/ta_func/ta_MACD.cp312-win_amd64.pyd
tabox/ta_func/ta_MACDEXT.cp312-win_amd64.pyd
tabox/ta_func/ta_MACDFIX.cp312-win_amd64.pyd
tabox/ta_func/ta_MAMA.cp312-win_amd64.pyd
tabox/ta_func/ta_MAVP.cp312-win_amd64.pyd
tabox/ta_func/ta_MAX.cp312-win_amd64.pyd
tabox/ta_func/ta_MAXINDEX.cp312-win_amd64.pyd
tabox/ta_func/ta_MEDPRICE.cp312-win_amd64.pyd
tabox/ta_func/ta_MFI.cp312-win_amd64.pyd
tabox/ta_func/ta_MIDPOINT.cp312-win_amd64.pyd
tabox/ta_func/ta_MIDPRICE.cp312-win_amd64.pyd
tabox/ta_func/ta_MIN.cp312-win_amd64.pyd
ta_box-0.0.1a1.dev5.dist-info/METADATA
ta_box-0.0.1a1.dev5.dist-info/WHEEL
ta_box-0.0.1a1.dev5.dist-info/top_level.txt
ta_box-0.0.1a1.dev5.dist-info/RECORD
