Metadata-Version: 2.4
Name: TA-Box
Version: 0.0.1a1.dev5
Summary: A Python implementation for TA-LIB
Home-page: https://github.com/quantmew/ta-lib
Author: Jun Wang
Author-email: jstzwj@aliyun.com
Project-URL: Bug Tracker, https://github.com/quantmew/ta-lib/issues
Classifier: Programming Language :: Python :: 3
Classifier: Operating System :: OS Independent
Requires-Python: >=3.6
License-File: LICENSE
Requires-Dist: numpy>=1.19.2
Requires-Dist: cython>=0.29.21
Dynamic: author
Dynamic: author-email
Dynamic: classifier
Dynamic: description
Dynamic: description-content-type
Dynamic: home-page
Dynamic: license-file
Dynamic: project-url
Dynamic: requires-dist
Dynamic: requires-python
Dynamic: summary
